flask_first/__init__.py
flask_first/swagger_ui.py
flask_first/first/__init__.py
flask_first/first/exceptions.py
flask_first/first/serializers.py
flask_first/first/specification.py
flask_first/first/validator.py
flask_first/first/loaders/__init__.py
flask_first/first/loaders/yaml_loader.py
flask_first/schema/custom_fields.py
flask_first/schema/schema_maker.py
flask_first/static/swagger_ui/favicon-16x16.png
flask_first/static/swagger_ui/favicon-32x32.png
flask_first/static/swagger_ui/index.css
flask_first/static/swagger_ui/oauth2-redirect.html
flask_first/static/swagger_ui/swagger-ui-bundle.js
flask_first/static/swagger_ui/swagger-ui-es-bundle-core.js
flask_first/static/swagger_ui/swagger-ui-es-bundle.js
flask_first/static/swagger_ui/swagger-ui-standalone-preset.js
flask_first/static/swagger_ui/swagger-ui.css
flask_first/static/swagger_ui/swagger-ui.js
flask_first/templates/swagger_ui/index.html
flask_first-0.20.0.dist-info/LICENSE
flask_first-0.20.0.dist-info/METADATA
flask_first-0.20.0.dist-info/WHEEL
flask_first-0.20.0.dist-info/top_level.txt
flask_first-0.20.0.dist-info/RECORD
