Metadata-Version: 2.2
Name: Flask-First
Version: 0.20.0
Summary: Flask extension for using 'specification first' or 'API-first' principle via OpenAPI specification.
Author-email: Konstantin Fadeev <fadeev@legalact.pro>
License: The MIT License (MIT)
Project-URL: changelog, https://github.com/flask-pro/flask-first/blob/master/CHANGES.md
Project-URL: repository, https://github.com/flask-pro/flask-first
Classifier: Framework :: Flask
Classifier: License :: OSI Approved :: MIT License
Classifier: Operating System :: OS Independent
Classifier: Programming Language :: Python :: 3
Requires-Python: >=3.9
License-File: LICENSE
Requires-Dist: Flask>=2.0.3
Requires-Dist: PyYAML>=6.0.1
Requires-Dist: openapi-spec-validator>=0.5.0
Requires-Dist: marshmallow>=3.14.1
Provides-Extra: dev
Requires-Dist: bandit==1.7.9; extra == "dev"
Requires-Dist: build==1.2.1; extra == "dev"
Requires-Dist: mypy==1.11.2; extra == "dev"
Requires-Dist: pre-commit==3.8.0; extra == "dev"
Requires-Dist: pytest==8.3.2; extra == "dev"
Requires-Dist: pytest-cov==5.0.0; extra == "dev"
Requires-Dist: python-dotenv==1.0.1; extra == "dev"
Requires-Dist: tox==4.18.0; extra == "dev"
Requires-Dist: twine==5.1.1; extra == "dev"
